{
  "courseId": "hsk1",
  "level": "HSK1",
  "_luminaNote": "HSK 3.0 一级：第 1 课为正式教材《你好！》。第 2–4 课当前为会话画布轻量验证用，可替换为正式内容。会话画布数据规范见同目录 DIALOGUE-CANVAS-DATA.md。后续课次请在本数组追加条目，并同步 vocab-distribution.json 与 lessonN.json。",
  "lessons": [
    {
      "lessonNo": 1,
      "id": "hsk1_lesson1",
      "file": "lesson1.json",
      "title": {
        "cn": "你好！",
        "zh": "你好！",
        "kr": "안녕하세요!",
        "en": "Hello!",
        "jp": "こんにちは！"
      },
      "sceneGoal": "学习见面问候、道别与道歉致谢等礼貌用语，区分「您」与「你」的使用情境",
      "subtitle": "问候 · 礼貌用语",
      "grammarTargets": ["您", "你", "您 / 你"],
      "vocabTargets": ["您", "你", "好", "你好", "谢谢", "不客气", "对不起", "没关系", "再见", "老师"],
      "extensionTargets": ["礼貌用语卡"],
      "displayTitle": {
        "cn": "第1课",
        "zh": "第1课",
        "kr": "제1과",
        "en": "Lesson 1",
        "jp": "第1課"
      }
    },
    {
      "lessonNo": 2,
      "id": "hsk1_lesson2",
      "file": "lesson2.json",
      "title": {
        "cn": "轻量验证",
        "zh": "轻量验证",
        "kr": "UI 검증",
        "en": "Canvas smoke test",
        "jp": "表示検証"
      },
      "subtitle": "HSK3.0 画布多课次",
      "displayTitle": {
        "cn": "第2课",
        "zh": "第2课",
        "kr": "제2과",
        "en": "Lesson 2",
        "jp": "第2課"
      }
    },
    {
      "lessonNo": 3,
      "id": "hsk1_lesson3",
      "file": "lesson3.json",
      "title": {
        "cn": "画布验证 L3",
        "zh": "画布验证 L3",
        "kr": "캔버스 L3",
        "en": "Canvas L3",
        "jp": "検証 L3"
      },
      "subtitle": "标题格式 · 行数",
      "displayTitle": {
        "cn": "第3课",
        "zh": "第3课",
        "kr": "제3과",
        "en": "Lesson 3",
        "jp": "第3課"
      }
    },
    {
      "lessonNo": 4,
      "id": "hsk1_lesson4",
      "file": "lesson4.json",
      "title": {
        "cn": "画布验证 L4",
        "zh": "画布验证 L4",
        "kr": "캔버스 L4",
        "en": "Canvas L4",
        "jp": "検証 L4"
      },
      "subtitle": "无 scene.title · 省略 speaker",
      "displayTitle": {
        "cn": "第4课",
        "zh": "第4课",
        "kr": "제4과",
        "en": "Lesson 4",
        "jp": "第4課"
      }
    }
  ]
}
